kontainer/__init__.py
kontainer/py.typed
kontainer/container/__init__.py
kontainer/container/maybe.py
kontainer/container/result.py
kontainer/core/__init__.py
kontainer/core/const.py
kontainer/core/exception.py
kontainer/core/types.py
kontainer/decorator/__init__.py
kontainer/decorator/option.py
kontainer/decorator/result.py
kontainer/flow/__init__.py
kontainer/flow/compose.py
kontainer/flow/convert.py
kontainer/flow/flip.py
kontainer/flow/flowtools.py
kontainer/flow/maps.py
kontainer/flow/pipe.py
kontainer/utils/__init__.py
kontainer/utils/generator.py
kontainer-0.2.3.dist-info/METADATA
kontainer-0.2.3.dist-info/WHEEL
kontainer-0.2.3.dist-info/licenses/LICENSE
kontainer-0.2.3.dist-info/RECORD
