Metadata-Version: 2.1
Name: kontainer
Version: 0.2.3
Summary: How to look like functional programming
Project-URL: Repository, https://github.com/phi-friday/kontainer
Author-email: phi <phi.friday@gmail.com>
License: MIT License
License-File: LICENSE
Classifier: Development Status :: 4 - Beta
Classifier: Programming Language :: Python :: 3
Classifier: Programming Language :: Python :: 3.8
Classifier: Programming Language :: Python :: 3.9
Classifier: Programming Language :: Python :: 3.10
Classifier: Programming Language :: Python :: 3.11
Classifier: Programming Language :: Python :: 3.12
Classifier: Programming Language :: Python :: Implementation :: CPython
Requires-Python: >=3.8
Requires-Dist: typing-extensions>=4.10.0
